{"_version": "2.0.0", "_events": [], "_notes": [{"_time": 11.320569538196848, "_lineIndex": 1, "_lineLayer": 0, "_type": 0, "_cutDirection": 8}, {"_time": 11.858471261078712, "_lineIndex": 3, "_lineLayer": 0, "_type": 1, "_cutDirection": 8}, {"_time": 14.038619060491742, "_lineIndex": 0, "_lineLayer": 0, "_type": 0, "_cutDirection": 8}, {"_time": 16.220374264538464, "_lineIndex": 0, "_lineLayer": 1, "_type": 1, "_cutDirection": 8}, {"_time": 19.501086612467628, "_lineIndex": 2, "_lineLayer": 0, "_type": 0, "_cutDirection": 8}, {"_time": 20.578164083126214, "_lineIndex": 3, "_lineLayer": 0, "_type": 1, "_cutDirection": 8}, {"_time": 21.67848296544092, "_lineIndex": 0, "_lineLayer": 0, "_type": 0, "_cutDirection": 8}, {"_time": 22.75865696827627, "_lineIndex": 3, "_lineLayer": 0, "_type": 1, "_cutDirection": 8}, {"_time": 23.86189689593289, "_lineIndex": 1, "_lineLayer": 0, "_type": 1, "_cutDirection": 8}, {"_time": 24.9402032771496, "_lineIndex": 0, "_lineLayer": 0, "_type": 0, "_cutDirection": 8}, {"_time": 26.041385510733893, "_lineIndex": 2, "_lineLayer": 0, "_type": 1, "_cutDirection": 8}, {"_time": 27.13856911019636, "_lineIndex": 0, "_lineLayer": 1, "_type": 1, "_cutDirection": 8}, {"_time": 28.219006747544523, "_lineIndex": 2, "_lineLayer": 0, "_type": 1, "_cutDirection": 8}, {"_time": 29.319576713173866, "_lineIndex": 2, "_lineLayer": 0, "_type": 1, "_cutDirection": 8}, {"_time": 30.398600772782956, "_lineIndex": 1, "_lineLayer": 0, "_type": 1, "_cutDirection": 8}, {"_time": 31.50078616787934, "_lineIndex": 2, "_lineLayer": 0, "_type": 0, "_cutDirection": 8}, {"_time": 32.578182088149696, "_lineIndex": 0, "_lineLayer": 0, "_type": 1, "_cutDirection": 8}, {"_time": 33.68188076048711, "_lineIndex": 0, "_lineLayer": 0, "_type": 0, "_cutDirection": 8}, {"_time": 34.76126592690706, "_lineIndex": 2, "_lineLayer": 0, "_type": 0, "_cutDirection": 8}, {"_time": 35.86127485319635, "_lineIndex": 1, "_lineLayer": 0, "_type": 1, "_cutDirection": 8}, {"_time": 36.95801641897146, "_lineIndex": 3, "_lineLayer": 0, "_type": 0, "_cutDirection": 8}, {"_time": 37.49952955513407, "_lineIndex": 1, "_lineLayer": 0, "_type": 1, "_cutDirection": 8}, {"_time": 38.03842343576381, "_lineIndex": 2, "_lineLayer": 0, "_type": 1, "_cutDirection": 8}, {"_time": 39.13807213487792, "_lineIndex": 0, "_lineLayer": 0, "_type": 0, "_cutDirection": 8}, {"_time": 40.00028206914151, "_lineIndex": 2, "_lineLayer": 0, "_type": 1, "_cutDirection": 8}, {"_time": 40.22171042588598, "_lineIndex": 2, "_lineLayer": 0, "_type": 0, "_cutDirection": 8}, {"_time": 41.10168035732345, "_lineIndex": 1, "_lineLayer": 0, "_type": 0, "_cutDirection": 8}, {"_time": 41.31862438696654, "_lineIndex": 2, "_lineLayer": 0, "_type": 1, "_cutDirection": 8}, {"_time": 41.86012797970846, "_lineIndex": 2, "_lineLayer": 0, "_type": 1, "_cutDirection": 8}, {"_time": 42.40060568788456, "_lineIndex": 1, "_lineLayer": 0, "_type": 0, "_cutDirection": 8}, {"_time": 43.49888580595242, "_lineIndex": 0, "_lineLayer": 0, "_type": 0, "_cutDirection": 8}, {"_time": 44.04004963917959, "_lineIndex": 2, "_lineLayer": 0, "_type": 1, "_cutDirection": 8}, {"_time": 44.58059466887197, "_lineIndex": 3, "_lineLayer": 1, "_type": 1, "_cutDirection": 8}, {"_time": 45.45815934272801, "_lineIndex": 1, "_lineLayer": 0, "_type": 0, "_cutDirection": 8}, {"_time": 45.68028381998124, "_lineIndex": 2, "_lineLayer": 0, "_type": 1, "_cutDirection": 8}, {"_time": 46.219287479415165, "_lineIndex": 2, "_lineLayer": 0, "_type": 1, "_cutDirection": 8}, {"_time": 46.76096209140343, "_lineIndex": 0, "_lineLayer": 0, "_type": 0, "_cutDirection": 8}, {"_time": 47.318684411086934, "_lineIndex": 2, "_lineLayer": 0, "_type": 1, "_cutDirection": 8}, {"_time": 47.86173243869818, "_lineIndex": 0, "_lineLayer": 0, "_type": 0, "_cutDirection": 8}, {"_time": 48.74166892170699, "_lineIndex": 2, "_lineLayer": 0, "_type": 1, "_cutDirection": 8}, {"_time": 48.958704999820725, "_lineIndex": 1, "_lineLayer": 0, "_type": 0, "_cutDirection": 8}, {"_time": 49.82184138822649, "_lineIndex": 3, "_lineLayer": 0, "_type": 1, "_cutDirection": 8}, {"_time": 50.0410902876979, "_lineIndex": 0, "_lineLayer": 0, "_type": 0, "_cutDirection": 8}, {"_time": 51.1399131635893, "_lineIndex": 1, "_lineLayer": 0, "_type": 0, "_cutDirection": 8}, {"_time": 51.680142015921525, "_lineIndex": 2, "_lineLayer": 0, "_type": 1, "_cutDirection": 8}, {"_time": 52.22152885796075, "_lineIndex": 0, "_lineLayer": 1, "_type": 0, "_cutDirection": 8}, {"_time": 53.31962688116274, "_lineIndex": 2, "_lineLayer": 0, "_type": 0, "_cutDirection": 8}, {"_time": 54.40160898906008, "_lineIndex": 0, "_lineLayer": 0, "_type": 1, "_cutDirection": 8}, {"_time": 55.49843038750107, "_lineIndex": 1, "_lineLayer": 0, "_type": 0, "_cutDirection": 8}, {"_time": 56.57925046043712, "_lineIndex": 3, "_lineLayer": 1, "_type": 0, "_cutDirection": 8}, {"_time": 57.680319239830936, "_lineIndex": 1, "_lineLayer": 0, "_type": 0, "_cutDirection": 8}, {"_time": 58.219567159257224, "_lineIndex": 2, "_lineLayer": 0, "_type": 0, "_cutDirection": 8}, {"_time": 58.77971979820151, "_lineIndex": 0, "_lineLayer": 0, "_type": 0, "_cutDirection": 8}, {"_time": 59.32068183539394, "_lineIndex": 3, "_lineLayer": 1, "_type": 1, "_cutDirection": 8}, {"_time": 59.86103212270635, "_lineIndex": 1, "_lineLayer": 0, "_type": 1, "_cutDirection": 8}, {"_time": 60.39886211408482, "_lineIndex": 2, "_lineLayer": 0, "_type": 1, "_cutDirection": 8}, {"_time": 60.96017345989587, "_lineIndex": 0, "_lineLayer": 0, "_type": 0, "_cutDirection": 8}, {"_time": 61.499062783325115, "_lineIndex": 3, "_lineLayer": 1, "_type": 1, "_cutDirection": 8}, {"_time": 61.82072344918084, "_lineIndex": 1, "_lineLayer": 0, "_type": 0, "_cutDirection": 8}, {"_time": 62.04070421935355, "_lineIndex": 2, "_lineLayer": 0, "_type": 0, "_cutDirection": 8}, {"_time": 62.918455470928755, "_lineIndex": 0, "_lineLayer": 0, "_type": 1, "_cutDirection": 8}, {"_time": 63.13917049846567, "_lineIndex": 1, "_lineLayer": 0, "_type": 0, "_cutDirection": 8}, {"_time": 63.679695662829815, "_lineIndex": 3, "_lineLayer": 0, "_type": 1, "_cutDirection": 8}, {"_time": 64.21964693557027, "_lineIndex": 0, "_lineLayer": 0, "_type": 0, "_cutDirection": 8}, {"_time": 64.78186024128406, "_lineIndex": 3, "_lineLayer": 1, "_type": 1, "_cutDirection": 8}, {"_time": 65.32069512282754, "_lineIndex": 1, "_lineLayer": 0, "_type": 0, "_cutDirection": 8}, {"_time": 66.17858370865021, "_lineIndex": 2, "_lineLayer": 0, "_type": 1, "_cutDirection": 8}, {"_time": 66.39853553817905, "_lineIndex": 1, "_lineLayer": 0, "_type": 0, "_cutDirection": 8}, {"_time": 67.27960029284512, "_lineIndex": 2, "_lineLayer": 0, "_type": 1, "_cutDirection": 8}, {"_time": 67.49856759032082, "_lineIndex": 1, "_lineLayer": 0, "_type": 1, "_cutDirection": 8}, {"_time": 68.03832774173867, "_lineIndex": 3, "_lineLayer": 1, "_type": 1, "_cutDirection": 8}, {"_time": 68.57980836481514, "_lineIndex": 2, "_lineLayer": 0, "_type": 0, "_cutDirection": 8}, {"_time": 69.14021501363024, "_lineIndex": 3, "_lineLayer": 0, "_type": 1, "_cutDirection": 8}, {"_time": 69.6797178567945, "_lineIndex": 0, "_lineLayer": 1, "_type": 1, "_cutDirection": 8}, {"_time": 70.75959783357206, "_lineIndex": 2, "_lineLayer": 0, "_type": 1, "_cutDirection": 8}, {"_time": 71.85857103523576, "_lineIndex": 2, "_lineLayer": 0, "_type": 1, "_cutDirection": 8}, {"_time": 72.93848648295213, "_lineIndex": 3, "_lineLayer": 1, "_type": 1, "_cutDirection": 8}, {"_time": 74.03864126008698, "_lineIndex": 2, "_lineLayer": 0, "_type": 0, "_cutDirection": 8}, {"_time": 74.91875165126321, "_lineIndex": 1, "_lineLayer": 0, "_type": 1, "_cutDirection": 8}, {"_time": 75.14050300979395, "_lineIndex": 0, "_lineLayer": 0, "_type": 1, "_cutDirection": 8}, {"_time": 75.9992190171312, "_lineIndex": 2, "_lineLayer": 0, "_type": 0, "_cutDirection": 8}, {"_time": 76.21997233348131, "_lineIndex": 3, "_lineLayer": 0, "_type": 1, "_cutDirection": 8}, {"_time": 76.78002575294352, "_lineIndex": 0, "_lineLayer": 1, "_type": 1, "_cutDirection": 8}, {"_time": 77.3206028662627, "_lineIndex": 2, "_lineLayer": 0, "_type": 1, "_cutDirection": 8}, {"_time": 77.85866114335867, "_lineIndex": 1, "_lineLayer": 0, "_type": 1, "_cutDirection": 8}, {"_time": 78.39813040983809, "_lineIndex": 3, "_lineLayer": 1, "_type": 1, "_cutDirection": 8}, {"_time": 79.27878101638252, "_lineIndex": 0, "_lineLayer": 0, "_type": 1, "_cutDirection": 8}, {"_time": 79.50002725364904, "_lineIndex": 2, "_lineLayer": 0, "_type": 0, "_cutDirection": 8}, {"_time": 79.81894882455543, "_lineIndex": 2, "_lineLayer": 0, "_type": 1, "_cutDirection": 8}, {"_time": 80.38180905785137, "_lineIndex": 0, "_lineLayer": 0, "_type": 1, "_cutDirection": 8}, {"_time": 80.5803583474688, "_lineIndex": 1, "_lineLayer": 0, "_type": 0, "_cutDirection": 8}, {"_time": 81.68014180237023, "_lineIndex": 1, "_lineLayer": 0, "_type": 0, "_cutDirection": 8}, {"_time": 81.68014180237023, "_lineIndex": 2, "_lineLayer": 0, "_type": 0, "_cutDirection": 8}, {"_time": 82.75865317032707, "_lineIndex": 1, "_lineLayer": 0, "_type": 1, "_cutDirection": 8}, {"_time": 83.10125212392857, "_lineIndex": 2, "_lineLayer": 0, "_type": 1, "_cutDirection": 8}, {"_time": 83.63888675947912, "_lineIndex": 0, "_lineLayer": 0, "_type": 1, "_cutDirection": 8}, {"_time": 83.86150206733849, "_lineIndex": 2, "_lineLayer": 0, "_type": 1, "_cutDirection": 8}, {"_time": 84.72194172846368, "_lineIndex": 0, "_lineLayer": 0, "_type": 1, "_cutDirection": 8}, {"_time": 84.95959728944803, "_lineIndex": 2, "_lineLayer": 0, "_type": 0, "_cutDirection": 8}, {"_time": 85.50004026418303, "_lineIndex": 2, "_lineLayer": 0, "_type": 1, "_cutDirection": 8}, {"_time": 86.03939556172952, "_lineIndex": 1, "_lineLayer": 0, "_type": 0, "_cutDirection": 8}, {"_time": 86.59917573934528, "_lineIndex": 3, "_lineLayer": 1, "_type": 0, "_cutDirection": 8}, {"_time": 87.14199835664519, "_lineIndex": 0, "_lineLayer": 0, "_type": 0, "_cutDirection": 8}, {"_time": 88.00138409746489, "_lineIndex": 2, "_lineLayer": 0, "_type": 0, "_cutDirection": 8}, {"_time": 88.21808567750791, "_lineIndex": 0, "_lineLayer": 0, "_type": 0, "_cutDirection": 8}, {"_time": 89.31842926200169, "_lineIndex": 1, "_lineLayer": 0, "_type": 0, "_cutDirection": 8}, {"_time": 90.40190423691162, "_lineIndex": 0, "_lineLayer": 0, "_type": 0, "_cutDirection": 8}, {"_time": 91.49884785233925, "_lineIndex": 3, "_lineLayer": 1, "_type": 1, "_cutDirection": 8}, {"_time": 92.57812435428876, "_lineIndex": 0, "_lineLayer": 0, "_type": 0, "_cutDirection": 8}, {"_time": 93.46133073087809, "_lineIndex": 1, "_lineLayer": 0, "_type": 0, "_cutDirection": 8}, {"_time": 93.67878303568624, "_lineIndex": 1, "_lineLayer": 0, "_type": 0, "_cutDirection": 8}, {"_time": 94.21841826299135, "_lineIndex": 1, "_lineLayer": 0, "_type": 0, "_cutDirection": 8}, {"_time": 94.75918708430086, "_lineIndex": 0, "_lineLayer": 0, "_type": 1, "_cutDirection": 8}, {"_time": 95.32190408653999, "_lineIndex": 2, "_lineLayer": 0, "_type": 1, "_cutDirection": 8}, {"_time": 95.86163772053975, "_lineIndex": 2, "_lineLayer": 0, "_type": 0, "_cutDirection": 8}, {"_time": 96.74134682738955, "_lineIndex": 1, "_lineLayer": 0, "_type": 0, "_cutDirection": 8}, {"_time": 96.96009771334697, "_lineIndex": 2, "_lineLayer": 0, "_type": 1, "_cutDirection": 8}, {"_time": 97.82140702520998, "_lineIndex": 1, "_lineLayer": 0, "_type": 1, "_cutDirection": 8}, {"_time": 98.0406686469426, "_lineIndex": 2, "_lineLayer": 0, "_type": 0, "_cutDirection": 8}, {"_time": 99.14059808102013, "_lineIndex": 1, "_lineLayer": 0, "_type": 0, "_cutDirection": 8}, {"_time": 99.14059808102013, "_lineIndex": 2, "_lineLayer": 0, "_type": 1, "_cutDirection": 8}, {"_time": 100.21978067042264, "_lineIndex": 2, "_lineLayer": 0, "_type": 1, "_cutDirection": 8}, {"_time": 101.10161540258377, "_lineIndex": 1, "_lineLayer": 0, "_type": 0, "_cutDirection": 8}, {"_time": 101.32068741916852, "_lineIndex": 2, "_lineLayer": 0, "_type": 0, "_cutDirection": 8}, {"_time": 102.17833806520672, "_lineIndex": 2, "_lineLayer": 0, "_type": 0, "_cutDirection": 8}, {"_time": 102.40091874133742, "_lineIndex": 1, "_lineLayer": 0, "_type": 0, "_cutDirection": 8}, {"_time": 103.50092462810923, "_lineIndex": 1, "_lineLayer": 0, "_type": 0, "_cutDirection": 8}, {"_time": 104.0598924144542, "_lineIndex": 2, "_lineLayer": 0, "_type": 1, "_cutDirection": 8}, {"_time": 104.58060828345654, "_lineIndex": 0, "_lineLayer": 1, "_type": 0, "_cutDirection": 8}, {"_time": 105.67903792147096, "_lineIndex": 3, "_lineLayer": 1, "_type": 1, "_cutDirection": 8}, {"_time": 106.76081445900195, "_lineIndex": 0, "_lineLayer": 1, "_type": 0, "_cutDirection": 8}, {"_time": 107.8605992907364, "_lineIndex": 0, "_lineLayer": 0, "_type": 1, "_cutDirection": 8}, {"_time": 108.94153861964071, "_lineIndex": 3, "_lineLayer": 1, "_type": 1, "_cutDirection": 8}, {"_time": 110.04153943238047, "_lineIndex": 1, "_lineLayer": 0, "_type": 1, "_cutDirection": 8}, {"_time": 111.11851248245101, "_lineIndex": 3, "_lineLayer": 1, "_type": 0, "_cutDirection": 8}, {"_time": 112.22163149670918, "_lineIndex": 0, "_lineLayer": 1, "_type": 0, "_cutDirection": 8}, {"_time": 113.31904004635734, "_lineIndex": 3, "_lineLayer": 0, "_type": 0, "_cutDirection": 8}, {"_time": 114.40077978191921, "_lineIndex": 3, "_lineLayer": 0, "_type": 0, "_cutDirection": 8}, {"_time": 115.49980992153563, "_lineIndex": 0, "_lineLayer": 0, "_type": 1, "_cutDirection": 8}, {"_time": 116.580909055073, "_lineIndex": 1, "_lineLayer": 0, "_type": 0, "_cutDirection": 8}, {"_time": 117.68135207752421, "_lineIndex": 3, "_lineLayer": 1, "_type": 1, "_cutDirection": 8}, {"_time": 118.75956676129896, "_lineIndex": 0, "_lineLayer": 0, "_type": 0, "_cutDirection": 8}, {"_time": 119.85990186950964, "_lineIndex": 2, "_lineLayer": 0, "_type": 1, "_cutDirection": 8}, {"_time": 120.93930173992122, "_lineIndex": 1, "_lineLayer": 0, "_type": 0, "_cutDirection": 8}, {"_time": 122.03906066809573, "_lineIndex": 0, "_lineLayer": 0, "_type": 0, "_cutDirection": 8}, {"_time": 123.13927642605027, "_lineIndex": 1, "_lineLayer": 0, "_type": 1, "_cutDirection": 8}, {"_time": 124.22193433369735, "_lineIndex": 2, "_lineLayer": 0, "_type": 0, "_cutDirection": 8}, {"_time": 125.32182783674044, "_lineIndex": 1, "_lineLayer": 0, "_type": 0, "_cutDirection": 8}, {"_time": 126.40050725377786, "_lineIndex": 3, "_lineLayer": 1, "_type": 1, "_cutDirection": 8}, {"_time": 127.4996441850609, "_lineIndex": 1, "_lineLayer": 0, "_type": 0, "_cutDirection": 8}, {"_time": 128.03927738953365, "_lineIndex": 2, "_lineLayer": 0, "_type": 0, "_cutDirection": 8}, {"_time": 128.58105701825428, "_lineIndex": 1, "_lineLayer": 0, "_type": 0, "_cutDirection": 8}, {"_time": 129.6798003824171, "_lineIndex": 0, "_lineLayer": 0, "_type": 0, "_cutDirection": 8}, {"_time": 130.76199000854467, "_lineIndex": 3, "_lineLayer": 1, "_type": 0, "_cutDirection": 8}, {"_time": 131.86007310688996, "_lineIndex": 1, "_lineLayer": 0, "_type": 0, "_cutDirection": 8}, {"_time": 132.7213484399126, "_lineIndex": 1, "_lineLayer": 0, "_type": 1, "_cutDirection": 8}, {"_time": 132.96197863456808, "_lineIndex": 2, "_lineLayer": 0, "_type": 1, "_cutDirection": 8}, {"_time": 133.50072371519306, "_lineIndex": 1, "_lineLayer": 0, "_type": 0, "_cutDirection": 8}, {"_time": 134.04008665764425, "_lineIndex": 2, "_lineLayer": 0, "_type": 1, "_cutDirection": 8}, {"_time": 135.12097029448879, "_lineIndex": 1, "_lineLayer": 0, "_type": 0, "_cutDirection": 8}, {"_time": 135.99961751932904, "_lineIndex": 2, "_lineLayer": 0, "_type": 1, "_cutDirection": 8}, {"_time": 136.21921774248096, "_lineIndex": 1, "_lineLayer": 0, "_type": 0, "_cutDirection": 8}, {"_time": 137.31986262932276, "_lineIndex": 1, "_lineLayer": 0, "_type": 0, "_cutDirection": 8}, {"_time": 137.8580748254543, "_lineIndex": 1, "_lineLayer": 0, "_type": 0, "_cutDirection": 8}, {"_time": 138.39902598950022, "_lineIndex": 2, "_lineLayer": 0, "_type": 1, "_cutDirection": 8}, {"_time": 139.49984856959065, "_lineIndex": 3, "_lineLayer": 1, "_type": 0, "_cutDirection": 8}, {"_time": 140.57940755831027, "_lineIndex": 1, "_lineLayer": 0, "_type": 1, "_cutDirection": 8}, {"_time": 141.68153720415336, "_lineIndex": 0, "_lineLayer": 0, "_type": 0, "_cutDirection": 8}, {"_time": 142.76072584448227, "_lineIndex": 1, "_lineLayer": 0, "_type": 1, "_cutDirection": 8}, {"_time": 143.32052807212918, "_lineIndex": 3, "_lineLayer": 1, "_type": 0, "_cutDirection": 8}, {"_time": 143.8614548374149, "_lineIndex": 1, "_lineLayer": 0, "_type": 0, "_cutDirection": 8}, {"_time": 144.93900928469094, "_lineIndex": 0, "_lineLayer": 0, "_type": 0, "_cutDirection": 8}, {"_time": 145.8200593965218, "_lineIndex": 2, "_lineLayer": 0, "_type": 1, "_cutDirection": 8}, {"_time": 146.04123568842368, "_lineIndex": 1, "_lineLayer": 0, "_type": 1, "_cutDirection": 8}, {"_time": 146.57981720919506, "_lineIndex": 0, "_lineLayer": 0, "_type": 0, "_cutDirection": 8}, {"_time": 147.1387707982698, "_lineIndex": 3, "_lineLayer": 0, "_type": 1, "_cutDirection": 8}, {"_time": 147.68053514546733, "_lineIndex": 1, "_lineLayer": 0, "_type": 1, "_cutDirection": 8}, {"_time": 148.22161091975218, "_lineIndex": 0, "_lineLayer": 0, "_type": 0, "_cutDirection": 8}, {"_time": 149.1012522635024, "_lineIndex": 1, "_lineLayer": 0, "_type": 1, "_cutDirection": 8}, {"_time": 149.31837434716903, "_lineIndex": 2, "_lineLayer": 0, "_type": 0, "_cutDirection": 8}, {"_time": 150.17924816968193, "_lineIndex": 2, "_lineLayer": 0, "_type": 0, "_cutDirection": 8}, {"_time": 150.3982115412151, "_lineIndex": 0, "_lineLayer": 1, "_type": 0, "_cutDirection": 8}, {"_time": 150.95999674099167, "_lineIndex": 3, "_lineLayer": 0, "_type": 0, "_cutDirection": 8}, {"_time": 151.50098392351802, "_lineIndex": 1, "_lineLayer": 0, "_type": 1, "_cutDirection": 8}, {"_time": 152.04043632756262, "_lineIndex": 0, "_lineLayer": 1, "_type": 1, "_cutDirection": 8}, {"_time": 152.58047689859987, "_lineIndex": 1, "_lineLayer": 0, "_type": 0, "_cutDirection": 8}, {"_time": 153.46076665340277, "_lineIndex": 2, "_lineLayer": 0, "_type": 1, "_cutDirection": 8}, {"_time": 153.67854942227927, "_lineIndex": 1, "_lineLayer": 0, "_type": 0, "_cutDirection": 8}, {"_time": 154.22127057874658, "_lineIndex": 2, "_lineLayer": 0, "_type": 1, "_cutDirection": 8}, {"_time": 154.53813920085818, "_lineIndex": 2, "_lineLayer": 0, "_type": 1, "_cutDirection": 8}, {"_time": 154.7817938257724, "_lineIndex": 1, "_lineLayer": 0, "_type": 1, "_cutDirection": 8}, {"_time": 155.32156981695704, "_lineIndex": 1, "_lineLayer": 0, "_type": 0, "_cutDirection": 8}, {"_time": 155.860900745589, "_lineIndex": 0, "_lineLayer": 0, "_type": 1, "_cutDirection": 8}, {"_time": 156.96032465774343, "_lineIndex": 3, "_lineLayer": 1, "_type": 0, "_cutDirection": 8}, {"_time": 157.8209575316383, "_lineIndex": 1, "_lineLayer": 0, "_type": 1, "_cutDirection": 8}, {"_time": 158.0395043246864, "_lineIndex": 2, "_lineLayer": 0, "_type": 0, "_cutDirection": 8}, {"_time": 159.13854557984504, "_lineIndex": 0, "_lineLayer": 0, "_type": 0, "_cutDirection": 8}, {"_time": 159.68077628862466, "_lineIndex": 2, "_lineLayer": 0, "_type": 0, "_cutDirection": 8}, {"_time": 160.22135834415903, "_lineIndex": 1, "_lineLayer": 0, "_type": 0, "_cutDirection": 8}, {"_time": 161.32121392856655, "_lineIndex": 2, "_lineLayer": 0, "_type": 1, "_cutDirection": 8}, {"_time": 161.63816862378943, "_lineIndex": 1, "_lineLayer": 0, "_type": 1, "_cutDirection": 8}, {"_time": 162.17898228399125, "_lineIndex": 2, "_lineLayer": 0, "_type": 0, "_cutDirection": 8}, {"_time": 162.39918763650567, "_lineIndex": 1, "_lineLayer": 0, "_type": 1, "_cutDirection": 8}, {"_time": 163.27924880973725, "_lineIndex": 1, "_lineLayer": 0, "_type": 0, "_cutDirection": 8}, {"_time": 163.49965492137878, "_lineIndex": 2, "_lineLayer": 0, "_type": 0, "_cutDirection": 8}, {"_time": 164.04178672082486, "_lineIndex": 1, "_lineLayer": 0, "_type": 0, "_cutDirection": 8}, {"_time": 164.58159048256869, "_lineIndex": 2, "_lineLayer": 0, "_type": 0, "_cutDirection": 8}, {"_time": 165.14197569685237, "_lineIndex": 1, "_lineLayer": 0, "_type": 0, "_cutDirection": 8}, {"_time": 165.6797275805085, "_lineIndex": 3, "_lineLayer": 1, "_type": 0, "_cutDirection": 8}, {"_time": 166.75839705639635, "_lineIndex": 1, "_lineLayer": 0, "_type": 1, "_cutDirection": 8}, {"_time": 167.64146143617378, "_lineIndex": 2, "_lineLayer": 0, "_type": 0, "_cutDirection": 8}, {"_time": 167.8604085482087, "_lineIndex": 1, "_lineLayer": 0, "_type": 1, "_cutDirection": 8}, {"_time": 168.39967107462874, "_lineIndex": 3, "_lineLayer": 1, "_type": 1, "_cutDirection": 8}, {"_time": 168.93926900868445, "_lineIndex": 1, "_lineLayer": 0, "_type": 0, "_cutDirection": 8}, {"_time": 169.49936876005358, "_lineIndex": 2, "_lineLayer": 0, "_type": 1, "_cutDirection": 8}, {"_time": 170.03961026091363, "_lineIndex": 1, "_lineLayer": 0, "_type": 0, "_cutDirection": 8}, {"_time": 170.92160945042704, "_lineIndex": 3, "_lineLayer": 1, "_type": 0, "_cutDirection": 8}, {"_time": 171.140327139191, "_lineIndex": 1, "_lineLayer": 0, "_type": 0, "_cutDirection": 8}, {"_time": 172.0016485180464, "_lineIndex": 2, "_lineLayer": 0, "_type": 0, "_cutDirection": 8}, {"_time": 172.22024093068873, "_lineIndex": 1, "_lineLayer": 0, "_type": 1, "_cutDirection": 8}, {"_time": 172.75826996384657, "_lineIndex": 3, "_lineLayer": 1, "_type": 1, "_cutDirection": 8}, {"_time": 173.31980852476568, "_lineIndex": 1, "_lineLayer": 0, "_type": 1, "_cutDirection": 8}, {"_time": 173.86098484250553, "_lineIndex": 3, "_lineLayer": 1, "_type": 1, "_cutDirection": 8}, {"_time": 174.4001490030634, "_lineIndex": 2, "_lineLayer": 0, "_type": 1, "_cutDirection": 8}, {"_time": 175.49856801372943, "_lineIndex": 1, "_lineLayer": 0, "_type": 0, "_cutDirection": 8}, {"_time": 176.57910598537362, "_lineIndex": 0, "_lineLayer": 1, "_type": 1, "_cutDirection": 8}, {"_time": 177.13955004086816, "_lineIndex": 3, "_lineLayer": 1, "_type": 1, "_cutDirection": 8}, {"_time": 177.6794711778524, "_lineIndex": 0, "_lineLayer": 0, "_type": 0, "_cutDirection": 8}, {"_time": 178.75820595345502, "_lineIndex": 2, "_lineLayer": 0, "_type": 1, "_cutDirection": 8}, {"_time": 179.86173185936764, "_lineIndex": 2, "_lineLayer": 0, "_type": 1, "_cutDirection": 8}, {"_time": 180.7413382102902, "_lineIndex": 0, "_lineLayer": 1, "_type": 0, "_cutDirection": 8}, {"_time": 180.9602081423799, "_lineIndex": 3, "_lineLayer": 1, "_type": 1, "_cutDirection": 8}, {"_time": 181.49826831664416, "_lineIndex": 1, "_lineLayer": 0, "_type": 0, "_cutDirection": 8}, {"_time": 182.03838524081613, "_lineIndex": 2, "_lineLayer": 0, "_type": 1, "_cutDirection": 8}, {"_time": 183.13899615247493, "_lineIndex": 2, "_lineLayer": 0, "_type": 0, "_cutDirection": 8}, {"_time": 183.9996807876148, "_lineIndex": 0, "_lineLayer": 0, "_type": 1, "_cutDirection": 8}, {"_time": 184.22031557207313, "_lineIndex": 2, "_lineLayer": 0, "_type": 1, "_cutDirection": 8}, {"_time": 185.09800983360174, "_lineIndex": 1, "_lineLayer": 0, "_type": 0, "_cutDirection": 8}, {"_time": 185.32194749126984, "_lineIndex": 2, "_lineLayer": 0, "_type": 1, "_cutDirection": 8}, {"_time": 185.86013090686063, "_lineIndex": 1, "_lineLayer": 0, "_type": 0, "_cutDirection": 8}, {"_time": 186.39893424466928, "_lineIndex": 1, "_lineLayer": 0, "_type": 1, "_cutDirection": 8}, {"_time": 186.95803150425405, "_lineIndex": 1, "_lineLayer": 0, "_type": 0, "_cutDirection": 8}, {"_time": 187.49879476745792, "_lineIndex": 3, "_lineLayer": 1, "_type": 1, "_cutDirection": 8}, {"_time": 188.57902907238864, "_lineIndex": 0, "_lineLayer": 0, "_type": 0, "_cutDirection": 8}, {"_time": 189.4606809358685, "_lineIndex": 2, "_lineLayer": 0, "_type": 0, "_cutDirection": 8}, {"_time": 189.67985625075715, "_lineIndex": 0, "_lineLayer": 0, "_type": 0, "_cutDirection": 8}, {"_time": 190.76138252686974, "_lineIndex": 2, "_lineLayer": 0, "_type": 0, "_cutDirection": 8}, {"_time": 191.32079798063768, "_lineIndex": 0, "_lineLayer": 0, "_type": 0, "_cutDirection": 8}, {"_time": 191.85897248494828, "_lineIndex": 3, "_lineLayer": 1, "_type": 1, "_cutDirection": 8}, {"_time": 192.95979694386776, "_lineIndex": 1, "_lineLayer": 0, "_type": 0, "_cutDirection": 8}, {"_time": 194.0414058832709, "_lineIndex": 2, "_lineLayer": 0, "_type": 1, "_cutDirection": 8}, {"_time": 194.58179334095593, "_lineIndex": 2, "_lineLayer": 0, "_type": 0, "_cutDirection": 8}, {"_time": 195.13854448158685, "_lineIndex": 0, "_lineLayer": 1, "_type": 0, "_cutDirection": 8}, {"_time": 196.22077057437014, "_lineIndex": 1, "_lineLayer": 0, "_type": 0, "_cutDirection": 8}, {"_time": 197.09977641177719, "_lineIndex": 2, "_lineLayer": 0, "_type": 1, "_cutDirection": 8}, {"_time": 197.32162855487644, "_lineIndex": 0, "_lineLayer": 0, "_type": 0, "_cutDirection": 8}, {"_time": 197.8590098951758, "_lineIndex": 2, "_lineLayer": 0, "_type": 0, "_cutDirection": 8}, {"_time": 198.1797213181393, "_lineIndex": 1, "_lineLayer": 0, "_type": 0, "_cutDirection": 8}, {"_time": 198.40071244761987, "_lineIndex": 2, "_lineLayer": 0, "_type": 0, "_cutDirection": 8}, {"_time": 198.96063950173817, "_lineIndex": 2, "_lineLayer": 0, "_type": 0, "_cutDirection": 8}, {"_time": 199.50171577201007, "_lineIndex": 0, "_lineLayer": 1, "_type": 0, "_cutDirection": 8}, {"_time": 200.03980083799024, "_lineIndex": 3, "_lineLayer": 1, "_type": 1, "_cutDirection": 8}, {"_time": 200.57996418135843, "_lineIndex": 1, "_lineLayer": 0, "_type": 1, "_cutDirection": 8}, {"_time": 201.46114907736916, "_lineIndex": 2, "_lineLayer": 0, "_type": 0, "_cutDirection": 8}, {"_time": 201.6793467847667, "_lineIndex": 0, "_lineLayer": 0, "_type": 0, "_cutDirection": 8}, {"_time": 202.55872427434633, "_lineIndex": 1, "_lineLayer": 0, "_type": 1, "_cutDirection": 8}, {"_time": 203.32039324390064, "_lineIndex": 3, "_lineLayer": 1, "_type": 1, "_cutDirection": 8}, {"_time": 203.85935915561362, "_lineIndex": 2, "_lineLayer": 0, "_type": 0, "_cutDirection": 8}, {"_time": 204.9597408899189, "_lineIndex": 0, "_lineLayer": 0, "_type": 0, "_cutDirection": 8}, {"_time": 205.82073140916154, "_lineIndex": 0, "_lineLayer": 0, "_type": 0, "_cutDirection": 8}, {"_time": 206.0405034344961, "_lineIndex": 1, "_lineLayer": 0, "_type": 1, "_cutDirection": 8}, {"_time": 206.5801097050292, "_lineIndex": 1, "_lineLayer": 0, "_type": 0, "_cutDirection": 8}, {"_time": 206.8985088136389, "_lineIndex": 2, "_lineLayer": 0, "_type": 1, "_cutDirection": 8}, {"_time": 207.1415058842266, "_lineIndex": 2, "_lineLayer": 0, "_type": 0, "_cutDirection": 8}, {"_time": 207.6793366025086, "_lineIndex": 2, "_lineLayer": 0, "_type": 1, "_cutDirection": 8}, {"_time": 208.21934425309098, "_lineIndex": 0, "_lineLayer": 0, "_type": 0, "_cutDirection": 8}, {"_time": 208.78139420041032, "_lineIndex": 2, "_lineLayer": 0, "_type": 1, "_cutDirection": 8}, {"_time": 209.32086389614534, "_lineIndex": 3, "_lineLayer": 1, "_type": 1, "_cutDirection": 8}, {"_time": 210.39983321495694, "_lineIndex": 2, "_lineLayer": 0, "_type": 1, "_cutDirection": 8}, {"_time": 211.4986074226992, "_lineIndex": 0, "_lineLayer": 1, "_type": 0, "_cutDirection": 8}, {"_time": 212.58126168149875, "_lineIndex": 3, "_lineLayer": 1, "_type": 1, "_cutDirection": 8}, {"_time": 213.67930298146402, "_lineIndex": 0, "_lineLayer": 1, "_type": 0, "_cutDirection": 8}, {"_time": 214.7599568118486, "_lineIndex": 3, "_lineLayer": 1, "_type": 0, "_cutDirection": 8}, {"_time": 215.8586230009367, "_lineIndex": 1, "_lineLayer": 0, "_type": 1, "_cutDirection": 8}, {"_time": 216.94093846408524, "_lineIndex": 1, "_lineLayer": 0, "_type": 1, "_cutDirection": 8}, {"_time": 218.0384407519875, "_lineIndex": 2, "_lineLayer": 0, "_type": 1, "_cutDirection": 8}, {"_time": 219.13854468357255, "_lineIndex": 2, "_lineLayer": 0, "_type": 1, "_cutDirection": 8}, {"_time": 220.21981272051787, "_lineIndex": 0, "_lineLayer": 0, "_type": 1, "_cutDirection": 8}, {"_time": 221.31843586138507, "_lineIndex": 1, "_lineLayer": 0, "_type": 1, "_cutDirection": 8}, {"_time": 222.39880435913625, "_lineIndex": 2, "_lineLayer": 0, "_type": 0, "_cutDirection": 8}, {"_time": 223.49990644257593, "_lineIndex": 0, "_lineLayer": 0, "_type": 1, "_cutDirection": 8}, {"_time": 224.03862643112333, "_lineIndex": 2, "_lineLayer": 0, "_type": 0, "_cutDirection": 8}, {"_time": 224.57997386834361, "_lineIndex": 1, "_lineLayer": 0, "_type": 0, "_cutDirection": 8}, {"_time": 225.67805101373344, "_lineIndex": 2, "_lineLayer": 0, "_type": 1, "_cutDirection": 8}, {"_time": 226.75875665182332, "_lineIndex": 1, "_lineLayer": 0, "_type": 0, "_cutDirection": 8}, {"_time": 227.86192187440176, "_lineIndex": 2, "_lineLayer": 0, "_type": 1, "_cutDirection": 8}, {"_time": 228.938360818976, "_lineIndex": 1, "_lineLayer": 0, "_type": 1, "_cutDirection": 8}, {"_time": 230.0403499394548, "_lineIndex": 2, "_lineLayer": 0, "_type": 1, "_cutDirection": 8}, {"_time": 231.12130724096667, "_lineIndex": 1, "_lineLayer": 0, "_type": 1, "_cutDirection": 8}, {"_time": 232.21822932735046, "_lineIndex": 2, "_lineLayer": 0, "_type": 0, "_cutDirection": 8}, {"_time": 234.39882726537513, "_lineIndex": 0, "_lineLayer": 0, "_type": 0, "_cutDirection": 8}, {"_time": 235.49966923974216, "_lineIndex": 2, "_lineLayer": 0, "_type": 0, "_cutDirection": 8}, {"_time": 236.3589590049034, "_lineIndex": 1, "_lineLayer": 0, "_type": 0, "_cutDirection": 8}, {"_time": 236.5805671235858, "_lineIndex": 2, "_lineLayer": 0, "_type": 0, "_cutDirection": 8}, {"_time": 238.75834266473933, "_lineIndex": 1, "_lineLayer": 0, "_type": 0, "_cutDirection": 8}, {"_time": 239.8592907473858, "_lineIndex": 1, "_lineLayer": 0, "_type": 1, "_cutDirection": 8}, {"_time": 240.94165160659813, "_lineIndex": 3, "_lineLayer": 0, "_type": 1, "_cutDirection": 8}, {"_time": 242.57991895644824, "_lineIndex": 0, "_lineLayer": 0, "_type": 1, "_cutDirection": 8}, {"_time": 243.6788571306815, "_lineIndex": 3, "_lineLayer": 0, "_type": 0, "_cutDirection": 8}, {"_time": 244.22128297724248, "_lineIndex": 1, "_lineLayer": 0, "_type": 1, "_cutDirection": 8}, {"_time": 245.08058352018242, "_lineIndex": 2, "_lineLayer": 0, "_type": 1, "_cutDirection": 8}, {"_time": 245.63918048046472, "_lineIndex": 1, "_lineLayer": 0, "_type": 0, "_cutDirection": 8}, {"_time": 246.39926523006895, "_lineIndex": 2, "_lineLayer": 0, "_type": 1, "_cutDirection": 8}, {"_time": 246.95948939553628, "_lineIndex": 1, "_lineLayer": 0, "_type": 1, "_cutDirection": 8}, {"_time": 247.49902243297555, "_lineIndex": 2, "_lineLayer": 0, "_type": 1, "_cutDirection": 8}, {"_time": 248.04072342225328, "_lineIndex": 0, "_lineLayer": 1, "_type": 1, "_cutDirection": 8}, {"_time": 248.581270925946, "_lineIndex": 1, "_lineLayer": 0, "_type": 0, "_cutDirection": 8}, {"_time": 249.67814776439536, "_lineIndex": 3, "_lineLayer": 0, "_type": 0, "_cutDirection": 8}, {"_time": 250.21805834649714, "_lineIndex": 1, "_lineLayer": 0, "_type": 0, "_cutDirection": 8}, {"_time": 250.5395677447166, "_lineIndex": 2, "_lineLayer": 0, "_type": 1, "_cutDirection": 8}, {"_time": 251.31812905367448, "_lineIndex": 1, "_lineLayer": 0, "_type": 1, "_cutDirection": 8}, {"_time": 251.86105796216137, "_lineIndex": 2, "_lineLayer": 0, "_type": 0, "_cutDirection": 8}, {"_time": 252.39970862460868, "_lineIndex": 0, "_lineLayer": 0, "_type": 1, "_cutDirection": 8}, {"_time": 252.9410908739491, "_lineIndex": 3, "_lineLayer": 1, "_type": 1, "_cutDirection": 8}, {"_time": 253.8194194275122, "_lineIndex": 1, "_lineLayer": 0, "_type": 1, "_cutDirection": 8}, {"_time": 254.04150006555574, "_lineIndex": 2, "_lineLayer": 0, "_type": 1, "_cutDirection": 8}, {"_time": 254.9197021982102, "_lineIndex": 1, "_lineLayer": 0, "_type": 0, "_cutDirection": 8}], "_obstacles": []}
